{
  "hash": "8f38561e",
  "configHash": "4fb2fda4",
  "lockfileHash": "f61896b6",
  "browserHash": "8ecb87c6",
  "optimized": {
    "react": {
      "src": "../../node_modules/react/index.js",
      "file": "react.js",
      "fileHash": "d7d61efb",
      "needsInterop": true
    },
    "react-dom/client": {
      "src": "../../node_modules/react-dom/client.js",
      "file": "react-dom_client.js",
      "fileHash": "615b05b1",
      "needsInterop": true
    },
    "react-router-dom": {
      "src": "../../node_modules/react-router-dom/dist/index.mjs",
      "file": "react-router-dom.js",
      "fileHash": "c380c24f",
      "needsInterop": false
    },
    "axios": {
      "src": "../../node_modules/axios/index.js",
      "file": "axios.js",
      "fileHash": "eccdd15e",
      "needsInterop": false
    }
  },
  "chunks": {
    "chunk-FYGYNQUM": {
      "file": "chunk-FYGYNQUM.js"
    },
    "chunk-32EALFBN": {
      "file": "chunk-32EALFBN.js"
    },
    "chunk-G3PMV62Z": {
      "file": "chunk-G3PMV62Z.js"
    }
  }
}